mixedassembly/__init__.py
mixedassembly/build_priors.py
mixedassembly/cli.py
mixedassembly/remove_frameshifts.py
mixedassembly/run_mixed_assembly.py
mixedassembly/utils.py
mixedassembly/utils_mixed_assembly.py
mixedassembly-0.2.1.dist-info/licenses/LICENSE
mixedassembly-0.2.1.dist-info/METADATA
mixedassembly-0.2.1.dist-info/WHEEL
mixedassembly-0.2.1.dist-info/entry_points.txt
mixedassembly-0.2.1.dist-info/top_level.txt
mixedassembly-0.2.1.dist-info/RECORD
