Metadata-Version: 2.4
Name: mixedassembly
Version: 0.2.1
Summary: Tools for consensus sequences mixing and frameshift correction (mixedAssembly)
Home-page: https://github.com/GERMAN00VP/mixedAssembly/tree/viralrecon_version
Author: Germán Vallejo Palma
Author-email: Germán Vallejo Palma <german.vallejo@isciii.es>
License: Attribution Permissive License (APL) 1.0
Project-URL: Homepage, https://github.com/GERMAN00VP/mixedAssembly/tree/viralrecon_version
Requires-Python: >=3.8
License-File: LICENSE
Requires-Dist: biopython>=1.79
Requires-Dist: numpy>=1.21
Requires-Dist: pandas>=1.3
Requires-Dist: pyarrow>=12.0
Dynamic: license-file
